<document xmlns:xlink="http://www.w3.org/1999/xlink" xmlns:z="http://www.ebi.ac.uk/z" source="Whatizit"><text><SENT sid="0" pm="."><plain>OBJECTIVE: To discuss the <z:hpo ids='HP_0011420'>death</z:hpo> affairs of gynecological patients and find the measurements of down-regulating the mortality </plain></SENT>
<SENT sid="1" pm="."><plain>METHODS: We conducted a retrospective study on the 54 <z:hpo ids='HP_0011420'>death</z:hpo> in-patients in our gynecological department during January 1993 and June 2008 </plain></SENT>
<SENT sid="2" pm="."><plain>Associated with literature, the data were analyzed according to <z:e sem="disease" ids="C0277554" disease_type="Disease or Syndrome" abbrv="">primary diseases</z:e>, <z:hpo ids='HP_0011420'>death</z:hpo> causes and clinical demonstrations, in order to probe into the rule of <z:hpo ids='HP_0011420'>death</z:hpo> in gynecological in-patients </plain></SENT>
<SENT sid="3" pm="."><plain>RESULTS: The main <z:hpo ids='HP_0011420'>death</z:hpo> causes were gynecological <z:e sem="disease" ids="C1306459,C0006826" disease_type="Neoplastic Process" abbrv="">cancers</z:e>, such as <z:mp ids='MP_0003579'>ovarian carcinoma</z:mp>, cervical <z:mp ids='MP_0002038'>carcinoma</z:mp>, <z:hpo ids='HP_0100768'>choriocarcinoma</z:hpo>, <z:e sem="disease" ids="C0008493" disease_type="Neoplastic Process" abbrv="">invasive mole</z:e> and <z:hpo ids='HP_0012114'>endometrial carcinoma</z:hpo>, which accounted for 79.6 percent (43/54) of gynecological <z:hpo ids='HP_0011420'>death</z:hpo> </plain></SENT>
<SENT sid="4" pm="."><plain><z:hpo ids='HP_0001699'>Sudden death</z:hpo> took up 24 percent (13/54), with <z:hpo ids='HP_0011420'>death</z:hpo> causes of cardio-<z:hpo ids='HP_0001297'>cerebral vascular events</z:hpo>, such as myocardium infarction, <z:hpo ids='HP_0002090'>pneumonia</z:hpo> embolism and <z:e sem="disease" ids="C0007780" disease_type="Disease or Syndrome" abbrv="">cerebral embolism</z:e> </plain></SENT>
<SENT sid="5" pm="."><plain>CONCLUSION: Gynecological <z:hpo ids='HP_0002664'>oncology</z:hpo> is still the main disease threatening women's lives </plain></SENT>
<SENT sid="6" pm="."><plain>Emphasis should be put on the physical and surgical complications of the patients </plain></SENT>
<SENT sid="7" pm="."><plain>We should attach more importance to the observation and associated treatment of post-operative and post-chemotherapeutic patients with high risks </plain></SENT>
</text></document>