<document xmlns:xlink="http://www.w3.org/1999/xlink" xmlns:z="http://www.ebi.ac.uk/z" source="Whatizit"><text><SENT sid="0" pm="."><plain>Cerebral emoli may originate in the heart, the carotid arterial system, or the aortic arch </plain></SENT>
<SENT sid="1" pm="."><plain>If the source of the <z:mpath ids='MPATH_110'>embolus</z:mpath> can be located, medical or surgical therapy may be able to prevent the occurrence of further <z:hpo ids='HP_0001297'>strokes</z:hpo> </plain></SENT>
</text></document>