<document xmlns:xlink="http://www.w3.org/1999/xlink" xmlns:z="http://www.ebi.ac.uk/z" source="Whatizit"><text><SENT sid="0" pm="."><plain>A pulmonary bronchovenous <z:mpath ids='MPATH_70'>fistula</z:mpath> is postulated as the possible cause of cerebral <z:mpath ids='MPATH_111'>air embolism</z:mpath> in a case of left-sided <z:hpo ids='HP_0002301'>hemiplegia</z:hpo> after penetrating chest trauma </plain></SENT>
<SENT sid="1" pm="."><plain>The possible mechanisms underlying the clinical picture, the consequences of cerebral <z:mpath ids='MPATH_111'>air embolism</z:mpath> and the management are briefly described </plain></SENT>
</text></document>