<document xmlns:xlink="http://www.w3.org/1999/xlink" xmlns:z="http://www.ebi.ac.uk/z" source="Whatizit"><text><SENT sid="0" pm="."><plain>BACKGROUND AND PURPOSE: Due to the increasing prevalence of <z:hpo ids='HP_0001635'>heart failure</z:hpo> (HF) and medical advances extending the life expectancy of patients with HF, physical therapists are often consulted to assist in the management of these patients in light of the benefits of exercise for them </plain></SENT>
<SENT sid="1" pm="."><plain>The purpose of this paper is to review the equipment and measures often encountered in patients with Stage D HF in the intensive care unit (ICU) and to discuss the care provided to two patients in this setting </plain></SENT>
<SENT sid="2" pm="."><plain>CASE DESCRIPTIONS: One patient was a 40-year-old man with Stage D HF on multiple inotropes receiving physical therapy intervention while awaiting a cardiac transplant </plain></SENT>
<SENT sid="3" pm="."><plain>The second patient was a 57-year-old man with Stage D HF due to ischemic <z:hpo ids='HP_0001638'>cardiomyopathy</z:hpo>, treated by physical therapy while receiving inotropic and intra-aortic balloon pump support, awaiting a renal and cardiac transplant </plain></SENT>
<SENT sid="4" pm="."><plain>DISCUSSION: Different physical therapy interventions were safely provided to both patients during their cardiac medical ICU courses </plain></SENT>
<SENT sid="5" pm="."><plain>Despite multiple medical issues requiring more complex decision making skills, this patient population may greatly benefit from physical therapy intervention </plain></SENT>
</text></document>