<document xmlns:xlink="http://www.w3.org/1999/xlink" xmlns:z="http://www.ebi.ac.uk/z" source="Whatizit"><text><SENT sid="0" pm="."><plain>RATIONALE: Lacunar <z:mpath ids='MPATH_124'>infarct</z:mpath> associated with small vessel disease is a common <z:hpo ids='HP_0001297'>stroke</z:hpo> subtype in China and has a favorable short-term prognosis </plain></SENT>
<SENT sid="1" pm="."><plain>Data on its long-term prognosis among Chinese patients are lacking </plain></SENT>
<SENT sid="2" pm="."><plain>AIMS: We aimed to study its long-term prognosis and predictors for poor outcomes </plain></SENT>
<SENT sid="3" pm="."><plain>DESIGN: We followed up to 75 consecutive Chinese <z:hpo ids='HP_0001297'>stroke</z:hpo> patients who had a lacunar <z:mpath ids='MPATH_124'>infarct</z:mpath> for a period of 5 years </plain></SENT>
<SENT sid="4" pm="."><plain>Clinical outcomes with respect to mortality and recurrent <z:hpo ids='HP_0001297'>stroke</z:hpo> were noted </plain></SENT>
<SENT sid="5" pm="."><plain>We evaluated baseline clinical and imaging predictors for such outcomes using the Cox regression analysis </plain></SENT>
<SENT sid="6" pm="."><plain>STUDY OUTCOMES: Sixteen (21.3%) patients died and 12 (16%) patients had recurrent <z:hpo ids='HP_0001297'>stroke</z:hpo> during follow-up </plain></SENT>
<SENT sid="7" pm="."><plain>Twenty-one (28%) patients had combined events of either <z:hpo ids='HP_0011420'>death</z:hpo> and/or recurrent <z:hpo ids='HP_0001297'>stroke</z:hpo> </plain></SENT>
<SENT sid="8" pm="."><plain>Univariate Cox regression analysis showed that age, literacy, National Institute of Health <z:hpo ids='HP_0001297'>Stroke</z:hpo> Scale, incident <z:hpo ids='HP_0001297'>stroke</z:hpo>/<z:hpo ids='HP_0002326'>transient ischemic attack</z:hpo>, and white matter lesion volume predicted survival, while, age, National Institute of Health <z:hpo ids='HP_0001297'>Stroke</z:hpo> Scale, systolic blood pressure, <z:e sem="disease" ids="C0598608" disease_type="Disease or Syndrome" abbrv="">hyperhomocysteinemia</z:e>, silent lacunes, microbleeds, and white matter lesion volume predicted recurrent <z:hpo ids='HP_0001297'>stroke</z:hpo> </plain></SENT>
<SENT sid="9" pm="."><plain>Multivariate Cox regression analysis showed that National Institute of Health <z:hpo ids='HP_0001297'>Stroke</z:hpo> Scale (HR 1.25, 95% CI 1.05-1.48) and white matter lesion volume (HR 1.46, 95% CI 1.11-1.92) predicted combined events of mortality and/or recurrent <z:hpo ids='HP_0001297'>stroke</z:hpo> after age adjustment </plain></SENT>
<SENT sid="10" pm="."><plain>CONCLUSION: Approximately one in four patients either died and/or had recurrent <z:hpo ids='HP_0001297'>stroke</z:hpo> within 5 years after a lacunar <z:mpath ids='MPATH_124'>infarct</z:mpath> </plain></SENT>
<SENT sid="11" pm="."><plain>Age, <z:hpo ids='HP_0001297'>stroke</z:hpo> severity, and volume of white matter lesion predict a poor long-term prognosis </plain></SENT>
</text></document>