<document xmlns:xlink="http://www.w3.org/1999/xlink" xmlns:z="http://www.ebi.ac.uk/z" source="Whatizit"><text><SENT sid="0" pm="."><plain>A 61-year-old man consulted for two long-standing ulcerations on the scalp and one on the nose, following an <z:hpo ids='HP_0011009'>acute</z:hpo> <z:e sem="disease" ids="C0042373" disease_type="Disease or Syndrome" abbrv="">vascular disorder</z:e> of the brain stem (<z:e sem="disease" ids="C0043019" disease_type="Disease or Syndrome" abbrv="">Wallenberg's syndrome</z:e>) </plain></SENT>
<SENT sid="1" pm="."><plain>The aetiology and pathogenesis of neurotrophic <z:mpath ids='MPATH_579'>ulcers</z:mpath> are briefly discussed </plain></SENT>
</text></document>