<document xmlns:xlink="http://www.w3.org/1999/xlink" xmlns:z="http://www.ebi.ac.uk/z" source="Whatizit"><text><SENT sid="0" pm="."><plain>Predisposing factors for <z:hpo ids='HP_0002647'>aortic dissection</z:hpo> are well known from necropsy series </plain></SENT>
<SENT sid="1" pm="."><plain>To evaluate the frequency of aortic and <z:e sem="disease" ids="C1260873" disease_type="Disease or Syndrome" abbrv="">aortic valve disease</z:e> in <z:hpo ids='HP_0002647'>aortic dissection</z:hpo> in vivo, 139 patients with <z:hpo ids='HP_0011009'>acute</z:hpo> <z:hpo ids='HP_0002647'>aortic dissection</z:hpo> (96 men, 43 women, mean age 60.5 +/- 15.7 years) were studied by transoesophageal echocardiography (TEE) using 3.5 and 5.0 MHz transducers </plain></SENT>
<SENT sid="2" pm="."><plain><z:hpo ids='HP_0001712'>Left ventricular hypertrophy</z:hpo> by TEE, defined as an end-diastolic wall thickness of the left ventricular septal wall over 1.5 cm, was found in 42 (67.7%) of 62 patients with type I, in 10 (58.8%) of 17 patients with type II and in 46 (76.7%) of 60 patients with type III dissection </plain></SENT>
<SENT sid="3" pm="."><plain>The mean value for the aortic root diameter was 3.2 +/- 1.3 cm.m-2 in type I dissection and 2.8 +/- 0.9 cm.m-2(ns) in type II dissection </plain></SENT>
<SENT sid="4" pm="."><plain>In the patient group with type III dissection this diameter was significantly smaller (1.8 +/- 0.9 cm.m-2; P &lt; 0.001) </plain></SENT>
<SENT sid="5" pm="."><plain>Thickening of aortic valve leaflets was demonstrated in six (9.7%) of 62 patients with <z:hpo ids='HP_0002647'>aortic dissection</z:hpo> type I (two of them with mild <z:hpo ids='HP_0001650'>aortic stenosis</z:hpo>), in two (11.8%) of 17 patients with <z:hpo ids='HP_0002647'>aortic dissection</z:hpo> type II and in 15 (25.0%) of 60 patients with <z:hpo ids='HP_0002647'>aortic dissection</z:hpo> type III </plain></SENT>
<SENT sid="6" pm="."><plain>A <z:hpo ids='HP_0001647'>bicuspid aortic valve</z:hpo> was diagnosed in five (6.3%) of 79 patients with <z:hpo ids='HP_0002647'>aortic dissection</z:hpo> types I and II and in one (1.7%) of 60 patients with type III dissection </plain></SENT>
<SENT sid="7" pm="."><plain>By colour coded Doppler echocardiography, <z:hpo ids='HP_0001659'>aortic regurgitation</z:hpo> was found in 46 (74.2%) of 62 patients with type I, 13 (76.5%) of 17 patients with type II and 23 (38.3%) of 60 patients with type III dissection.(ABSTRACT TRUNCATED AT 250 WORDS) </plain></SENT>
</text></document>