<document xmlns:xlink="http://www.w3.org/1999/xlink" xmlns:z="http://www.ebi.ac.uk/z" source="Whatizit"><text><SENT sid="0" pm="."><plain>Various mechanisms have been proposed to explain the pathogenesis of infantile <z:hpo ids='HP_0000501'>glaucoma</z:hpo> in the <z:e sem="disease" ids="C0038505" disease_type="Disease or Syndrome;Congenital Abnormality" abbrv="PKWS">Sturge-Weber syndrome</z:e> </plain></SENT>
<SENT sid="1" pm="."><plain>We report the results of treating six patients with combined trabeculectomy and cyclocryotherapy </plain></SENT>
<SENT sid="2" pm="."><plain>Successful control of the intraocular pressure occurred in <z:hpo ids='HP_0000001'>all</z:hpo> patients </plain></SENT>
<SENT sid="3" pm="."><plain>Two patients required a second procedure at another site </plain></SENT>
<SENT sid="4" pm="."><plain>We feel that the success of this procedure provides evidence that the <z:hpo ids='HP_0000501'>glaucoma</z:hpo> is secondary to elevated episcleral venous pressure in this condition </plain></SENT>
</text></document>