<document xmlns:xlink="http://www.w3.org/1999/xlink" xmlns:z="http://www.ebi.ac.uk/z" source="Whatizit"><text><SENT sid="0" pm="."><plain>A 20-year-old man with <z:e sem="disease" ids="C0004943" disease_type="Disease or Syndrome" abbrv="">Behcet's disease</z:e> characterized by recurrent arterial <z:hpo ids='HP_0002617'>aneurysms</z:hpo> presented with a new aortic root <z:hpo ids='HP_0002617'>aneurysm</z:hpo> </plain></SENT>
<SENT sid="1" pm="."><plain>This patient previously had <z:hpo ids='HP_0002617'>aneurysms</z:hpo> of the coronary arteries and vein, as well as ruptured renal artery <z:hpo ids='HP_0002617'>aneurysm</z:hpo> </plain></SENT>
<SENT sid="2" pm="."><plain><z:hpo ids='HP_0011010'>Chronic</z:hpo> maintenance immunosuppressive therapy was recommended due to the catastrophic nature of the disease, which the patient refused to take </plain></SENT>
<SENT sid="3" pm="."><plain>The patient died shortly after admission </plain></SENT>
<SENT sid="4" pm="."><plain>This case demonstrates the unique catastrophic natural history of vascular <z:e sem="disease" ids="C0004943" disease_type="Disease or Syndrome" abbrv="">Behcet's disease</z:e> with recurrent life-threatening arterial events, and this case stresses the therapeutic dilemma of maintenance immunosuppressive therapy in selected patients </plain></SENT>
</text></document>